logisticbank/__init__.py
logisticbank/logistic_regression_module.py
logisticbank-0.0.3.dist-info/METADATA
logisticbank-0.0.3.dist-info/WHEEL
logisticbank-0.0.3.dist-info/top_level.txt
logisticbank-0.0.3.dist-info/RECORD
